Workbook

Sheet Inputs
A1: Financial model (live formulas): Equipment finance for clean energy storage
A2: Month | B2: Cash | C2: Revenue | D2: Opex | E2: Net burn | F2: Source record
A3: 2025-03 | B3: 2294167 | C3: 39740.1 | D3: 145573.11 | E3: 105833.01 | F3: financial_snapshot:b11e4697-0950-49c0-8e36-07286a2fa79f
A4: 2025-04 | B4: 2185216.3 | C4: 45285.21 | D4: 154235.87 | E4: 108950.66 | F4: financial_snapshot:03a7091b-dad7-4e04-a8fa-dd9266b81b99
A5: 2025-05 | B5: 2085353.8 | C5: 51508.65 | D5: 151371.16 | E5: 99862.51 | F5: financial_snapshot:d012e1a9-9be2-40f9-815e-b2eaa9a97fb4
A6: 2025-06 | B6: 1980641.2 | C6: 53262.67 | D6: 157975.25 | E6: 104712.58 | F6: financial_snapshot:2f1c4279-a2ed-4c03-85cf-07a1105a6d2c
A7: 2025-07 | B7: 1884772 | C7: 54715.36 | D7: 150584.6 | E7: 95869.24 | F7: financial_snapshot:3deef059-b6e2-4941-a536-2c625bec5be6
A8: 2025-08 | B8: 1781484.8 | C8: 55577.86 | D8: 158865.06 | E8: 103287.2 | F8: financial_snapshot:ee553875-44ce-49bc-8e68-ac202512a95a
A9: 2025-09 | B9: 1682357.6 | C9: 56458.27 | D9: 155585.48 | E9: 99127.21 | F9: financial_snapshot:de8c3cb9-5f13-438b-ace3-5f9965bb8602
A10: 2025-10 | B10: 1592320 | C10: 67740.75 | D10: 157778.31 | E10: 90037.56 | F10: financial_snapshot:83af873f-db67-4ff2-89f8-13299465b36c
A11: 2025-11 | B11: 1499107.9 | C11: 68603.39 | D11: 161815.56 | E11: 93212.17 | F11: financial_snapshot:19b8eb3a-6867-4d14-9c5b-7cb4e61e7836
A12: 2025-12 | B12: 1404604.1 | C12: 71764.61 | D12: 166268.36 | E12: 94503.75 | F12: financial_snapshot:7e30183c-dbd0-439b-aeaf-7cdb4156ec60
A13: 2026-01 | B13: 1307954.3 | C13: 72660.96 | D13: 169310.78 | E13: 96649.82 | F13: financial_snapshot:4b5acaa3-dd72-4592-89bc-3d1e4538cd1e
A14: 2026-02 | B14: 1205120.2 | C14: 76280.01 | D14: 179114.12 | E14: 102834.11 | F14: financial_snapshot:7d1a51cf-6054-4eaa-a2ef-b2e94ce932dd
... A20: 2026-08 | B20: 690224.04 | C20: 102649.51 | D20: 185686.15 | E20: 83036.64 | F20: financial_snapshot:0ad90de9-c335-4f14-a208-14e3f52705b2

Sheet Assumptions
A1: Assumption | B1: Value | C1: How it is derived
A2: Currency | B2: USD | C2: organisation profile / snapshots
A3: Revenue growth per month | B3: =IFERROR((Inputs!C20/Inputs!C17)^(1/3)-1,0) | C3: formula: compound monthly growth over the last 3 months of Inputs
A4: Opex growth per month | B4: =IFERROR((Inputs!D20/Inputs!D17)^(1/3)-1,0) | C4: formula: compound monthly growth over the last 3 months of Inputs
A5: Minimum cash buffer | B5: 0 | C5: setting MIN_CASH_BUFFER
A6: Raise amount | B6: 3000000 | C6: organisation profile raise target (input)
A7: Raise month (1 = next month) | B7: 4 | C7: opportunity deadline + class decision lag (config/forecast.yaml)
A8: Probability applied to the raise | B8: 0.1 | C8: stage probability (config/scoring/reference.yaml)

Sheet Projection
A1: Month # | B1: Month | C1: Revenue | D1: Opex | E1: Net burn | F1: Inflow | G1: Cash (end)
A2: 1 | B2: =IFERROR(EDATE(DATEVALUE(Inputs!A20&"-01"),1),"") | C2: =Inputs!C20*(1+Assumptions!$B$3) | D2: =Inputs!D20*(1+Assumptions!$B$4) | E2: =D2-C2 | F2: =IF(A2=Assumptions!$B$7,Assumptions!$B$6*Assumptions!$B$8,0) | G2: =Inputs!B20-E2+F2
A3: 2 | B3: =IFERROR(EDATE(DATEVALUE(Inputs!A20&"-01"),2),"") | C3: =C2*(1+Assumptions!$B$3) | D3: =D2*(1+Assumptions!$B$4) | E3: =D3-C3 | F3: =IF(A3=Assumptions!$B$7,Assumptions!$B$6*Assumptions!$B$8,0) | G3: =G2-E3+F3
A4: 3 | B4: =IFERROR(EDATE(DATEVALUE(Inputs!A20&"-01"),3),"") | C4: =C3*(1+Assumptions!$B$3) | D4: =D3*(1+Assumptions!$B$4) | E4: =D4-C4 | F4: =IF(A4=Assumptions!$B$7,Assumptions!$B$6*Assumptions!$B$8,0) | G4: =G3-E4+F4
A5: 4 | B5: =IFERROR(EDATE(DATEVALUE(Inputs!A20&"-01"),4),"") | C5: =C4*(1+Assumptions!$B$3) | D5: =D4*(1+Assumptions!$B$4) | E5: =D5-C5 | F5: =IF(A5=Assumptions!$B$7,Assumptions!$B$6*Assumptions!$B$8,0) | G5: =G4-E5+F5
A6: 5 | B6: =IFERROR(EDATE(DATEVALUE(Inputs!A20&"-01"),5),"") | C6: =C5*(1+Assumptions!$B$3) | D6: =D5*(1+Assumptions!$B$4) | E6: =D6-C6 | F6: =IF(A6=Assumptions!$B$7,Assumptions!$B$6*Assumptions!$B$8,0) | G6: =G5-E6+F6
A7: 6 | B7: =IFERROR(EDATE(DATEVALUE(Inputs!A20&"-01"),6),"") | C7: =C6*(1+Assumptions!$B$3) | D7: =D6*(1+Assumptions!$B$4) | E7: =D7-C7 | F7: =IF(A7=Assumptions!$B$7,Assumptions!$B$6*Assumptions!$B$8,0) | G7: =G6-E7+F7
A8: 7 | B8: =IFERROR(EDATE(DATEVALUE(Inputs!A20&"-01"),7),"") | C8: =C7*(1+Assumptions!$B$3) | D8: =D7*(1+Assumptions!$B$4) | E8: =D8-C8 | F8: =IF(A8=Assumptions!$B$7,Assumptions!$B$6*Assumptions!$B$8,0) | G8: =G7-E8+F8
A9: 8 | B9: =IFERROR(EDATE(DATEVALUE(Inputs!A20&"-01"),8),"") | C9: =C8*(1+Assumptions!$B$3) | D9: =D8*(1+Assumptions!$B$4) | E9: =D9-C9 | F9: =IF(A9=Assumptions!$B$7,Assumptions!$B$6*Assumptions!$B$8,0) | G9: =G8-E9+F9
A10: 9 | B10: =IFERROR(EDATE(DATEVALUE(Inputs!A20&"-01"),9),"") | C10: =C9*(1+Assumptions!$B$3) | D10: =D9*(1+Assumptions!$B$4) | E10: =D10-C10 | F10: =IF(A10=Assumptions!$B$7,Assumptions!$B$6*Assumptions!$B$8,0) | G10: =G9-E10+F10
A11: 10 | B11: =IFERROR(EDATE(DATEVALUE(Inputs!A20&"-01"),10),"") | C11: =C10*(1+Assumptions!$B$3) | D11: =D10*(1+Assumptions!$B$4) | E11: =D11-C11 | F11: =IF(A11=Assumptions!$B$7,Assumptions!$B$6*Assumptions!$B$8,0) | G11: =G10-E11+F11
A12: 11 | B12: =IFERROR(EDATE(DATEVALUE(Inputs!A20&"-01"),11),"") | C12: =C11*(1+Assumptions!$B$3) | D12: =D11*(1+Assumptions!$B$4) | E12: =D12-C12 | F12: =IF(A12=Assumptions!$B$7,Assumptions!$B$6*Assumptions!$B$8,0) | G12: =G11-E12+F12
A13: 12 | B13: =IFERROR(EDATE(DATEVALUE(Inputs!A20&"-01"),12),"") | C13: =C12*(1+Assumptions!$B$3) | D13: =D12*(1+Assumptions!$B$4) | E13: =D13-C13 | F13: =IF(A13=Assumptions!$B$7,Assumptions!$B$6*Assumptions!$B$8,0) | G13: =G12-E13+F13
A14: 13 | B14: =IFERROR(EDATE(DATEVALUE(Inputs!A20&"-01"),13),"") | C14: =C13*(1+Assumptions!$B$3) | D14: =D13*(1+Assumptions!$B$4) | E14: =D14-C14 | F14: =IF(A14=Assumptions!$B$7,Assumptions!$B$6*Assumptions!$B$8,0) | G14: =G13-E14+F14
A15: 14 | B15: =IFERROR(EDATE(DATEVALUE(Inputs!A20&"-01"),14),"") | C15: =C14*(1+Assumptions!$B$3) | D15: =D14*(1+Assumptions!$B$4) | E15: =D15-C15 | F15: =IF(A15=Assumptions!$B$7,Assumptions!$B$6*Assumptions!$B$8,0) | G15: =G14-E15+F15
A16: 15 | B16: =IFERROR(EDATE(DATEVALUE(Inputs!A20&"-01"),15),"") | C16: =C15*(1+Assumptions!$B$3) | D16: =D15*(1+Assumptions!$B$4) | E16: =D16-C16 | F16: =IF(A16=Assumptions!$B$7,Assumptions!$B$6*Assumptions!$B$8,0) | G16: =G15-E16+F16
A17: 16 | B17: =IFERROR(EDATE(DATEVALUE(Inputs!A20&"-01"),16),"") | C17: =C16*(1+Assumptions!$B$3) | D17: =D16*(1+Assumptions!$B$4) | E17: =D17-C17 | F17: =IF(A17=Assumptions!$B$7,Assumptions!$B$6*Assumptions!$B$8,0) | G17: =G16-E17+F17
A18: 17 | B18: =IFERROR(EDATE(DATEVALUE(Inputs!A20&"-01"),17),"") | C18: =C17*(1+Assumptions!$B$3) | D18: =D17*(1+Assumptions!$B$4) | E18: =D18-C18 | F18: =IF(A18=Assumptions!$B$7,Assumptions!$B$6*Assumptions!$B$8,0) | G18: =G17-E18+F18
A19: 18 | B19: =IFERROR(EDATE(DATEVALUE(Inputs!A20&"-01"),18),"") | C19: =C18*(1+Assumptions!$B$3) | D19: =D18*(1+Assumptions!$B$4) | E19: =D19-C19 | F19: =IF(A19=Assumptions!$B$7,Assumptions!$B$6*Assumptions!$B$8,0) | G19: =G18-E19+F19
A20: 19 | B20: =IFERROR(EDATE(DATEVALUE(Inputs!A20&"-01"),19),"") | C20: =C19*(1+Assumptions!$B$3) | D20: =D19*(1+Assumptions!$B$4) | E20: =D20-C20 | F20: =IF(A20=Assumptions!$B$7,Assumptions!$B$6*Assumptions!$B$8,0) | G20: =G19-E20+F20
A21: 20 | B21: =IFERROR(EDATE(DATEVALUE(Inputs!A20&"-01"),20),"") | C21: =C20*(1+Assumptions!$B$3) | D21: =D20*(1+Assumptions!$B$4) | E21: =D21-C21 | F21: =IF(A21=Assumptions!$B$7,Assumptions!$B$6*Assumptions!$B$8,0) | G21: =G20-E21+F21
A22: 21 | B22: =IFERROR(EDATE(DATEVALUE(Inputs!A20&"-01"),21),"") | C22: =C21*(1+Assumptions!$B$3) | D22: =D21*(1+Assumptions!$B$4) | E22: =D22-C22 | F22: =IF(A22=Assumptions!$B$7,Assumptions!$B$6*Assumptions!$B$8,0) | G22: =G21-E22+F22
A23: 22 | B23: =IFERROR(EDATE(DATEVALUE(Inputs!A20&"-01"),22),"") | C23: =C22*(1+Assumptions!$B$3) | D23: =D22*(1+Assumptions!$B$4) | E23: =D23-C23 | F23: =IF(A23=Assumptions!$B$7,Assumptions!$B$6*Assumptions!$B$8,0) | G23: =G22-E23+F23
A24: 23 | B24: =IFERROR(EDATE(DATEVALUE(Inputs!A20&"-01"),23),"") | C24: =C23*(1+Assumptions!$B$3) | D24: =D23*(1+Assumptions!$B$4) | E24: =D24-C24 | F24: =IF(A24=Assumptions!$B$7,Assumptions!$B$6*Assumptions!$B$8,0) | G24: =G23-E24+F24
A25: 24 | B25: =IFERROR(EDATE(DATEVALUE(Inputs!A20&"-01"),24),"") | C25: =C24*(1+Assumptions!$B$3) | D25: =D24*(1+Assumptions!$B$4) | E25: =D25-C25 | F25: =IF(A25=Assumptions!$B$7,Assumptions!$B$6*Assumptions!$B$8,0) | G25: =G24-E25+F25

Sheet Runway
A1: Runway (months until cash < buffer) | B1: =IFERROR(MATCH(TRUE,INDEX(Projection!G2:G25<Assumptions!$B$5,0),0),"beyond 24 months")
A2: Zero-cash month | B2: =IFERROR(TEXT(INDEX(Projection!B2:B25,B1),"yyyy-mm"),"beyond the horizon")
A3: Starting cash | B3: =Inputs!B20
A4: Latest monthly net burn | B4: =Inputs!E20

Sheet Evidence
A1: # | B1: Reference | C1: Record | D1: Source
B2: financial_snapshot:b11e4697-0950-49c0-8e36-07286a2fa79f | C2: financial snapshot 2025-03 | D2: imported financials
B3: financial_snapshot:03a7091b-dad7-4e04-a8fa-dd9266b81b99 | C3: financial snapshot 2025-04 | D3: imported financials
B4: financial_snapshot:d012e1a9-9be2-40f9-815e-b2eaa9a97fb4 | C4: financial snapshot 2025-05 | D4: imported financials
B5: financial_snapshot:2f1c4279-a2ed-4c03-85cf-07a1105a6d2c | C5: financial snapshot 2025-06 | D5: imported financials
B6: financial_snapshot:3deef059-b6e2-4941-a536-2c625bec5be6 | C6: financial snapshot 2025-07 | D6: imported financials
B7: financial_snapshot:ee553875-44ce-49bc-8e68-ac202512a95a | C7: financial snapshot 2025-08 | D7: imported financials
B8: financial_snapshot:de8c3cb9-5f13-438b-ace3-5f9965bb8602 | C8: financial snapshot 2025-09 | D8: imported financials
B9: financial_snapshot:83af873f-db67-4ff2-89f8-13299465b36c | C9: financial snapshot 2025-10 | D9: imported financials
B10: financial_snapshot:19b8eb3a-6867-4d14-9c5b-7cb4e61e7836 | C10: financial snapshot 2025-11 | D10: imported financials
B11: financial_snapshot:7e30183c-dbd0-439b-aeaf-7cdb4156ec60 | C11: financial snapshot 2025-12 | D11: imported financials
B12: financial_snapshot:4b5acaa3-dd72-4592-89bc-3d1e4538cd1e | C12: financial snapshot 2026-01 | D12: imported financials
B13: financial_snapshot:7d1a51cf-6054-4eaa-a2ef-b2e94ce932dd | C13: financial snapshot 2026-02 | D13: imported financials
... B22: organization:11942a7b-a024-4a7d-b463-92f9a6f45c62#profile.raise_target | C22: raise target | D22: organisation profile
